slipstream/__init__.py
slipstream/__version__.py
slipstream/caching.py
slipstream/checkpointing.py
slipstream/codecs.py
slipstream/core.py
slipstream/interfaces.py
slipstream/utils.py
slipstream_async-1.0.5.dist-info/licenses/LICENSE
slipstream_async-1.0.5.dist-info/METADATA
slipstream_async-1.0.5.dist-info/WHEEL
slipstream_async-1.0.5.dist-info/top_level.txt
slipstream_async-1.0.5.dist-info/RECORD
