Metadata-Version: 2.4
Name: slipstream-async
Version: 1.0.5
Summary: Streamline your stream processing.
Author-email: Menziess <stefan_schenk@hotmail.com>
License: MIT
Project-URL: repository, https://github.com/Menziess/slipstream
Project-URL: documentation, https://slipstream.readthedocs.io
Keywords: python,streaming,kafka,stream-processing,data-engineering,dataflow,data-processing,streaming-data,slipstream,stateful-streaming
Classifier: Intended Audience :: Developers
Classifier: Intended Audience :: Science/Research
Classifier: Programming Language :: Python :: 3.10
Classifier: Programming Language :: Python :: 3.11
Classifier: Programming Language :: Python :: 3.12
Classifier: License :: OSI Approved :: MIT License
Classifier: Topic :: Scientific/Engineering
Classifier: Topic :: Scientific/Engineering :: Artificial Intelligence
Requires-Python: >=3.10
License-File: LICENSE
Provides-Extra: kafka
Requires-Dist: aiokafka; extra == "kafka"
Provides-Extra: cache
Requires-Dist: rocksdict; extra == "cache"
Provides-Extra: dev
Requires-Dist: pre-commit; extra == "dev"
Requires-Dist: pyright; extra == "dev"
Requires-Dist: ruff; extra == "dev"
Provides-Extra: test
Requires-Dist: pytest; extra == "test"
Requires-Dist: pytest-cov; extra == "test"
Requires-Dist: pytest-mock; extra == "test"
Requires-Dist: pytest-asyncio; extra == "test"
Requires-Dist: testcontainers[kafka]; extra == "test"
Provides-Extra: docs
Requires-Dist: sphinx; extra == "docs"
Requires-Dist: furo; extra == "docs"
Requires-Dist: sphinx-autoapi; extra == "docs"
Requires-Dist: sphinx-autobuild; extra == "docs"
Dynamic: license-file
